iphone_framer.py
iphone_framer-1.3.0.dist-info/METADATA
iphone_framer-1.3.0.dist-info/WHEEL
iphone_framer-1.3.0.dist-info/entry_points.txt
iphone_framer-1.3.0.dist-info/RECORD
