Metadata-Version: 2.4
Name: iphone-framer
Version: 1.3.0
Summary: iPhone Screenshot Frame Generator for App Store
Project-URL: Homepage, https://github.com/dcai/iphone-framer
Project-URL: Repository, https://github.com/dcai/iphone-framer
Author-email: Dongsheng Cai <pypi-contact@tux.im>
License: MIT
Keywords: app-store,frame,generator,iphone,screenshot
Classifier: Development Status :: 4 - Beta
Classifier: Intended Audience :: Developers
Classifier: License :: OSI Approved :: MIT License
Classifier: Programming Language :: Python :: 3
Classifier: Programming Language :: Python :: 3.8
Classifier: Programming Language :: Python :: 3.9
Classifier: Programming Language :: Python :: 3.10
Classifier: Programming Language :: Python :: 3.11
Classifier: Programming Language :: Python :: 3.12
Requires-Python: >=3.8
Requires-Dist: pillow>=9.0.0
